README.md
setup.cfg
setup.py
PyKsonLib/__init__.py
PyKsonLib/models.py
PyKsonLib.egg-info/PKG-INFO
PyKsonLib.egg-info/SOURCES.txt
PyKsonLib.egg-info/dependency_links.txt
PyKsonLib.egg-info/requires.txt
PyKsonLib.egg-info/top_level.txt